setup.py
bosh_dumpRes.egg-info/PKG-INFO
bosh_dumpRes.egg-info/SOURCES.txt
bosh_dumpRes.egg-info/dependency_links.txt
bosh_dumpRes.egg-info/not-zip-safe
bosh_dumpRes.egg-info/requires.txt
bosh_dumpRes.egg-info/top_level.txt
dumpRes/__init__.py
dumpRes/bojson2file.py
dumpRes/borestful.py
dumpRes/boshExcel.py