Metadata-Version: 1.0
Name: bosh-dumpRes
Version: 0.0.2
Summary: dump BigObject query result as a file
Home-page: https://github.com/macrodatalab/dumpRes.git
Author: MacroData Inc
Author-email: info@macrodatalab.com
License: Apache 2.0
Keywords: bigobject,macrodata,dump,command line tool,CSV,XLSX
Platform: UNKNOWN
